stocaching/__init__.py
stocaching-0.2.1.dist-info/LICENSE
stocaching-0.2.1.dist-info/METADATA
stocaching-0.2.1.dist-info/WHEEL
stocaching-0.2.1.dist-info/RECORD
