Metadata-Version: 2.1
Name: stocaching
Version: 0.2.1
Summary: A tiny library for stochastic dataset caching in PyTorch.
License: MIT
Author: C Jones
Author-email: cj1917@ic.ac.uk
Requires-Python: >=3.10,<3.13
Classifier: License :: OSI Approved :: MIT License
Classifier: Programming Language :: Python :: 3
Classifier: Programming Language :: Python :: 3.10
Classifier: Programming Language :: Python :: 3.11
Classifier: Programming Language :: Python :: 3.12
Requires-Dist: numpy (>=1.26.1,<2.0.0)
Requires-Dist: torch (>=2.1.0,<3.0.0)
